{
  "values": [
    {"id":"wizard_terra_cuiros:the_community","required":false},
    {"id":"wizard_terra_cuiros:mana_polarizer","required":false},

    {"id":"wizard_terra_cuiros:iron_mana_band","required":false},
    {"id":"wizard_terra_cuiros:iron_mana_flower","required":false},
    {"id":"wizard_terra_cuiros:iron_mana_cloak","required":false},
    {"id":"wizard_terra_cuiros:iron_magic_cuffs","required":false},
    {"id":"wizard_terra_cuiros:iron_celestial_magnet","required":false},
    {"id":"wizard_terra_cuiros:iron_celestial_cuffs","required":false},
    {"id":"wizard_terra_cuiros:iron_magnet_flower","required":false},
    {"id":"wizard_terra_cuiros:iron_celestial_emblem","required":false},
    {"id":"wizard_terra_cuiros:iron_arcane_flower","required":false},

    {"id":"wizard_terra_cuiros:summoner_emblem","required":false},
    {"id":"wizard_terra_cuiros:uniter_emblem","required":false},
    {"id":"wizard_terra_cuiros:doom_emblem","required":false},
    {"id":"wizard_terra_cuiros:necromantic_scroll","required":false},
    {"id":"wizard_terra_cuiros:hercules_beetle","required":false},
    {"id":"wizard_terra_cuiros:papyrus_scarab","required":false},
    {"id":"wizard_terra_cuiros:chaos_stone","required":false},

    {"id":"wizard_terra_cuiros:pygmy_necklace","required":false},
    {"id":"wizard_terra_cuiros:neptunes_shell","required":false},
    {"id":"wizard_terra_cuiros:moon_charm","required":false},
    {"id":"wizard_terra_cuiros:moon_shell","required":false},
    {"id":"wizard_terra_cuiros:celestial_shell","required":false},

    {"id":"wizard_terra_cuiros:iron_gold_crown","required":false},
    {"id":"wizard_terra_cuiros:iron_tarnished_crown","required":false},

    {"id":"wizard_terra_cuiros:discount_card","required":false},
    {"id":"wizard_terra_cuiros:lucky_coin","required":false},
    {"id":"wizard_terra_cuiros:gold_ring","required":false},
    {"id":"wizard_terra_cuiros:coin_ring","required":false},
    {"id":"wizard_terra_cuiros:greedy_ring","required":false},

    {"id":"wizard_terra_cuiros:chlorophyte_quiver","required":false},
    {"id":"wizard_terra_cuiros:deadshot_brooch","required":false},
    {"id":"wizard_terra_cuiros:elemental_quiver","required":false},

    {"id":"wizard_terra_cuiros:dark_focus","required":false},
    {"id":"wizard_terra_cuiros:soul_focus","required":false},
    {"id":"wizard_terra_cuiros:warped_focus","required":false},
    {"id":"wizard_terra_cuiros:goety_focus","required":false},
    {"id":"wizard_terra_cuiros:haunted_focus","required":false},

    {"id":"wizard_terra_cuiros:brewer_hat","required":false},
    {"id":"wizard_terra_cuiros:master_brewer_hat","required":false},
    {"id":"wizard_terra_cuiros:dimensional_soul_artifact","required":false},
    {"id":"wizard_terra_cuiros:sigil_of_calamitas","required":false},
    {"id":"wizard_terra_cuiros:ethereal_talisman","required":false},

    {"id":"wizard_terra_cuiros:spirit_brooch","required":false},
    {"id":"wizard_terra_cuiros:necklace_of_the_soulstained_edge","required":false},
    {"id":"wizard_terra_cuiros:necklace_of_the_deliverance_edge","required":false},

    {"id":"wizard_terra_cuiros:golden_shower","required":false},
    {"id":"wizard_terra_cuiros:ichor_arrow","required":false},
    {"id":"wizard_terra_cuiros:flask_of_ichor","required":false},

    {"id":"wizard_terra_cuiros:assassin_scope","required":false},
    {"id":"wizard_terra_cuiros:rapid_fire_scope","required":false},

    {"id":"wizard_terra_cuiros:rover_drive","required":false},
    {"id":"wizard_terra_cuiros:wulfrum_battery","required":false},
    {"id":"wizard_terra_cuiros:the_sponge","required":false},

    {"id":"wizard_terra_cuiros:deific_amulet","required":false},
    {"id":"wizard_terra_cuiros:honey_dew","required":false},
    {"id":"wizard_terra_cuiros:living_dew","required":false},
    {"id":"wizard_terra_cuiros:radiant_ooze","required":false},
    {"id":"wizard_terra_cuiros:ambrosial_ampoule","required":false}
  ]
}